airflow_env_patch/__init__.py
airflow_env_patch-0.1.dist-info/METADATA
airflow_env_patch-0.1.dist-info/WHEEL
airflow_env_patch-0.1.dist-info/top_level.txt
airflow_env_patch-0.1.dist-info/RECORD
